<?xml version="1.0"?>
<!DOCTYPE hibernate-mapping PUBLIC "-//Hibernate/Hibernate Mapping DTD 3.0//EN"
"http://www.hibernate.org/dtd/hibernate-mapping-3.0.dtd">
<!-- Generated Jul 24, 2016 4:29:10 PM by Hibernate Tools 4.0.1.Final -->
<hibernate-mapping>
	<class name="com.gotn.entity.PymeNdDetCli" table="PYME_ND_DET_CLI">
		<id name="ndclidId" type="long">
			<column name="NDCLID_ID" precision="10" scale="0" />
			<generator class="assigned" />
		</id>
		<many-to-one name="pymeProductos" class="com.gotn.entity.PymeProductos"
			fetch="select">
			<column name="PRODUC_ID" precision="18" scale="0" />
		</many-to-one>
		<many-to-one name="pymeNdEncCli" class="com.gotn.entity.PymeNdEncCli"
			fetch="select">
			<column name="NDCLI_ID" precision="18" scale="0" not-null="true" />
		</many-to-one>
		<property name="ndclidCantidad" type="java.lang.Long">
			<column name="NDCLID_CANTIDAD" precision="10" scale="0" />
		</property>
		<property name="ndclidDetalle" type="string">
			<column name="NDCLID_DETALLE" length="100" />
		</property>
		<property name="ndclidTotalLineaLocal" type="big_decimal">
			<column name="NDCLID_TOTAL_LINEA_LOCAL" precision="18" scale="3" />
		</property>
		<property name="ndclidTotalLineaExt" type="string">
			<column name="NDCLID_TOTAL_LINEA_EXT" length="20" />
		</property>
		<property name="ndclidCreadoPor" type="string">
			<column name="NDCLID_CREADO_POR" length="50" />
		</property>
		<property name="ndclidCreadoEl" type="date">
			<column name="NDCLID_CREADO_EL" length="7" />
		</property>
	</class>
</hibernate-mapping>
